{
"ARN": "0101",
"ATQ": "0102",
"LEG": "0103",
"DRK": "0104",
"FEM": "0105",
"ICE": "0106",
"HML": "0107",
"ALL": "0108",
"MIR": "0109",
"VIS": "0110",
"WTH": "0111",
"TMP": "0112",
"STH": "0113",
"EXO": "0114",
"USG": "0115",
"ULG": "0116",
"UDS": "0117",
"MMQ": "0118",
"NEM": "0119",
"PCY": "0120",
"INV": "0121",
"PLS": "0122",
"APC": "0123",
"ODY": "0124",
"TOR": "0125",
"JUD": "0126",
"ONS": "0127",
"LGN": "0128",
"SCG": "0129",
"MRD": "0201",
"DST": "0202",
"5DN": "0203",
"CHK": "0204",
"BOK": "0205",
"SOK": "0206",
"RAV": "0207",
"GPT": "0208",
"DIS": "0209",
"CSP": "0210",
"TSP": "0211",
"TSB": "0212",
"PLC": "0213",
"FUT": "0214",
"LRW": "0215",
"MOR": "0216",
"SHM": "0217",
"EVE": "0218",
"ALA": "0219",
"CON": "0220",
"ARB": "0221",
"ZEN": "0222",
"WWK": "0223",
"ROE": "0224",
"SOM": "0225",
"MBS": "0226",
"NPH": "0227",
"ISD": "0228",
"DKA": "0229",
"AVR": "0230",
"RTR": "0231",
"GTC": "0232",
"DGM": "0233",
"THS": "0234",
"BNG": "0235",
"JOU": "0236",
"KTK": "0238",
"FRF": "0239",
"DTK": "0240",
"BFZ": "0241",
"OGW": "0242",
"SOI": "0243",
"EMN": "0244",
"KLD": "0245",
"AER": "0246",
"AKH": "0247",
"HOU": "0248",
"XLN": "0249",
"RIX": "0250",
"DOM": "0251",
"GRN": "0252",
"RNA": "0253",
"WAR": "0254",
"ELD": "0255",
"THB": "0256",
"IKO": "0257",
"ZNR": "0258",
"ZNE": "0259",
"KHM": "0260",
"KHC": "0261",
"STX": "0262",
"STA": "0263",
"AFR": "0264",
"AFC": "0265",
"MID": "0266",
"MIC": "0267",
"VOW": "0268",
"VOC": "0269",
"DBL": "0270",
"NEO": "0271",
"NEC": "0272",
"SNC": "0273",
"NCC": "0274",
"DMU": "0275",
"DMC": "0276",
"BRO": "0277",
"BRR": "0278",
"BRC": "0279",
"ONE": "0280",
"ONC": "0281",
"MOM": "0282",
"MOC": "0283",
"MUL": "0284",
"MAT": "0285",
"WOE": "0286",
"WOC": "0287",
"LCI": "0288",
"LCC": "0289",
"REX": "0290",
"MKM": "0291",
"MKC": "0292",
"OTJ": "0293",
"BIG": "0294",
"OTP": "0295",
"OTC": "0296",
"BLB": "0297",
"BLC": "0298",
"DSK": "0299",
"DSC": "0230",
"FDN": "0301",
"FDC": "0302",
"DFT": "0303",
"DFC": "0304",
"TDM": "0305",
"TDC": "0306",
"FIN": "0307",
"FCA": "0308",
"FIC": "0309",
"EOE": "0310",
"EOS": "0311",
"EOC": "0312",
"SPM": "0313",
"SPE": "0314",
"MAR": "0315",
"TLA": "0316",
"LEA": "1601",
"LEB": "1602",
"2ED": "1603",
"3ED": "1604",
"4ED": "1605",
"CHR": "1606",
"5ED": "1608",
"6ED": "1609",
"7ED": "1610",
"8ED": "1611",
"9ED": "1612",
"10E": "1613",
"M10": "1614",
"M11": "1615",
"M12": "1616",
"M13": "1617",
"M14": "1618",
"M15": "1619",
"ORI": "1620",
"M19": "1621",
"M20": "1622",
"M21": "1623",
"UGL": "2701",
"UHG": "2702",
"UST": "2703",
"UND": "2704",
"UNF": "2705",
"STR": "2711",
"POR": "2712",
"PO2": "2713",
"POK": "2714",
"JMP": "3700",
"J22": "3701",
"J25": "3702",
"MMA": "3715",
"MM2": "3716",
"MM3": "3717",
"EMA": "3718",
"IMA": "3719",
"A25": "3720",
"2XM": "3721",
"2X2": "3722",
"TSR": "3730",
"DMR": "3731",
"RVR": "3732",
"INR": "3733",
"UMA": "3739",
"MH1": "3740",
"MH2": "3741",
"MH3": "3742",
"LTR": "3746",
"LTC": "3747",
"MB1": "3822",
"MB2": "3823",
"H09": "4727",
"PD2": "4728",
"PD3": "4729",
"P12": "4730",
"CMD": "5731",
"CMA": "5732",
"C13": "5733",
"C14": "5734",
"C15": "5735",
"C16": "5736",
"C17": "5737",
"C18": "5738",
"C19": "5739",
"C20": "5740",
"C21": "5741",
"CMR": "5743",
"CLB": "5744",
"40K": "5745",
"WHO": "5746",
"PIP": "5747",
"ACR": "5748",
"CNS": "5750",
"CN2": "5751",
"BBD": "5752",
"SS1": "6750",
"SS2": "6751",
"SS3": "6752",
"CLU": "6753",
"CC1": "6760",
"CC2": "6761",
"SLD": "7090",
"SLU": "7091",
"EXP": "7100",
"MPS": "7101",
"MPS2": "7102",
"SPG": "7103",
"CEI": "8000",
"CED": "8001",
"30A": "8002",
"Other": "0999"
}
